penelope/__init__.py
penelope/_purgatory/store_corpus.py
penelope/co_occurrence/__init__.py
penelope/co_occurrence/bundle.py
penelope/co_occurrence/convert.py
penelope/co_occurrence/hal_or_glove/__init__.py
penelope/co_occurrence/hal_or_glove/co_occurrence_ui.py
penelope/co_occurrence/hal_or_glove/compute_hal_or_glove.py
penelope/co_occurrence/hal_or_glove/vectorizer_glove.py
penelope/co_occurrence/hal_or_glove/vectorizer_hal.py
penelope/co_occurrence/interface.py
penelope/co_occurrence/keyness.py
penelope/co_occurrence/persistence.py
penelope/co_occurrence/prepare.py
penelope/co_occurrence/utility.py
penelope/co_occurrence/vectorize.py
penelope/co_occurrence/windows.py
penelope/common/__init__.py
penelope/common/cluster_analysis.py
penelope/common/curve_fit.py
penelope/common/dehyphenation/__init__.py
penelope/common/dehyphenation/swe_dehyphen.py
penelope/common/dehyphenation/utility.py
penelope/common/distance_metrics.py
penelope/common/goodness_of_fit.py
penelope/common/inject.py
penelope/common/keyness/__init__.py
penelope/common/keyness/hal_cwr.py
penelope/common/keyness/metrics.py
penelope/common/mdw.py
penelope/common/method_registry.py
penelope/common/pca_analysis.py
penelope/common/preprocess.py
penelope/common/tokenize/README.md
penelope/common/tokenize/__init__.py
penelope/common/tokenize/resources/bettertokenizer.sv
penelope/common/tokenize/resources/bettertokenizer.sv.saldo-tokens
penelope/common/tokenize/resources/punkt-nltk-svenska.pickle
penelope/common/tokenize/sparv_tokenize.py
penelope/common/tokenize/stopwords.py
penelope/corpus/__init__.py
penelope/corpus/document_index.py
penelope/corpus/dtm/__init__.py
penelope/corpus/dtm/convert.py
penelope/corpus/dtm/corpus.py
penelope/corpus/dtm/group.py
penelope/corpus/dtm/interface.py
penelope/corpus/dtm/optimize.py
penelope/corpus/dtm/slice.py
penelope/corpus/dtm/stats.py
penelope/corpus/dtm/store.py
penelope/corpus/dtm/ttm.py
penelope/corpus/dtm/ttm_legacy.py
penelope/corpus/dtm/vectorizer.py
humlab_penelope-0.8.3.dist-info/METADATA
humlab_penelope-0.8.3.dist-info/WHEEL
humlab_penelope-0.8.3.dist-info/entry_points.txt
humlab_penelope-0.8.3.dist-info/RECORD
