Metadata-Version: 2.3
Name: humlab-penelope
Version: 0.8.3
Summary: Utilities that simplify enelpeing in Jupyter Lab
License: Apache-2.0
Author: Roger Mähler
Author-email: roger.mahler@hotmail.com
Requires-Python: ==3.11.*
Classifier: License :: OSI Approved :: Apache Software License
Classifier: Operating System :: OS Independent
Classifier: Programming Language :: Python
Classifier: Programming Language :: Python :: 3
Classifier: Programming Language :: Python :: 3.11
Classifier: Topic :: Software Development
Provides-Extra: full
Requires-Dist: PyYAML ; extra == "full"
Requires-Dist: bokeh
Requires-Dist: click ; extra == "full"
Requires-Dist: ftfy
Requires-Dist: gensim ; extra == "full"
Requires-Dist: ipycytoscape
Requires-Dist: ipydatagrid (>=1.1.8,<2.0.0)
Requires-Dist: ipyfilechooser
Requires-Dist: ipywidgets
Requires-Dist: jupyter_bokeh
Requires-Dist: loguru
Requires-Dist: lxml
Requires-Dist: more_itertools
Requires-Dist: msgpack (>=1.0.2,<2.0.0)
Requires-Dist: networkx (>=3.1,<4.0)
Requires-Dist: nltk (>=3.5,<4.0)
Requires-Dist: numpy
Requires-Dist: openpyxl (>=3.0.5,<4.0.0)
Requires-Dist: pandas
Requires-Dist: pyarrow ; extra == "full"
Requires-Dist: python-dotenv
Requires-Dist: regex
Requires-Dist: requests (>=2.24.0,<3.0.0)
Requires-Dist: scipy (==1.12.0)
Requires-Dist: smart-open (>=6.4)
Requires-Dist: spacy (==3.7.0) ; extra == "full"
Requires-Dist: textacy ; extra == "full"
Requires-Dist: toml
Requires-Dist: tqdm
Requires-Dist: urllib3
Requires-Dist: wordcloud ; extra == "full"
Project-URL: Homepage, https://github.com/humlab/penelope
Project-URL: Repository, https://github.com/humlab/penelope
